{
	"Shortsword": {
		"type": "WEAPON",
		"icon": 1713,
		"level": 1,
		"goldCost": 1,
		"blurb": "",
		"coolDown": 0,
		"subType": "SWORD",
		"material": "metal1",
		"stackSize": 1
	},
	"Champion's Greatsword": {
		"type": "WEAPON",
		"icon": 1717,
		"level": 2,
		"goldCost": 1,
		"blurb": "",
		"coolDown": 0,
		"subType": "SWORD",
		"material": "metal1",
		"stackSize": 1
	},
	"Steelforged Sword": {
		"type": "WEAPON",
		"icon": 1719,
		"level": 3,
		"goldCost": 1,
		"blurb": "",
		"coolDown": 0,
		"subType": "SWORD",
		"material": "metal1",
		"stackSize": 1
	},
	"Corrupted Sword": {
		"type": "WEAPON",
		"icon": 1720,
		"level": 4,
		"goldCost": 1,
		"blurb": "",
		"coolDown": 0,
		"subType": "SWORD",
		"material": "metal1",
		"stackSize": 1
	},
	"Crusader's Warblade": {
		"type": "WEAPON",
		"icon": 1721,
		"level": 5,
		"goldCost": 1,
		"blurb": "",
		"coolDown": 0,
		"subType": "SWORD",
		"material": "metal1",
		"stackSize": 1
	},
	"Bloodforged Sword": {
		"type": "WEAPON",
		"icon": 1722,
		"level": 6,
		"goldCost": 1,
		"blurb": "",
		"coolDown": 0,
		"subType": "SWORD",
		"material": "metal1",
		"stackSize": 1
	},
	"Crystalforged Sword": {
		"type": "WEAPON",
		"icon": 1723,
		"level": 7,
		"goldCost": 1,
		"blurb": "",
		"coolDown": 0,
		"subType": "SWORD",
		"material": "metal1",
		"stackSize": 1
	},
	"Heart Stopper": {
		"type": "WEAPON",
		"icon": 1724,
		"level": 8,
		"goldCost": 1,
		"blurb": "",
		"coolDown": 0,
		"subType": "SWORD",
		"material": "metal1",
		"stackSize": 1
	},
	"Blade of Angels": {
		"type": "WEAPON",
		"icon": 1725,
		"level": 9,
		"goldCost": 1,
		"blurb": "",
		"coolDown": 0,
		"subType": "SWORD",
		"material": "metal1",
		"stackSize": 1
	},
	"Apocalypse": {
		"type": "WEAPON",
		"icon": 1732,
		"level": 10,
		"goldCost": 1,
		"blurb": "",
		"coolDown": 0,
		"subType": "SWORD",
		"material": "metal1",
		"stackSize": 1
	},
	"Carving Knife": {
		"type": "WEAPON",
		"icon": 1551,
		"level": 1,
		"goldCost": 1,
		"blurb": "",
		"coolDown": 0,
		"subType": "DAGGER",
		"material": "metal1",
		"stackSize": 1
	},
	"Fine Shanker": {
		"type": "WEAPON",
		"icon": 1555,
		"level": 2,
		"goldCost": 1,
		"blurb": "",
		"coolDown": 0,
		"subType": "DAGGER",
		"material": "metal1",
		"stackSize": 1
	},
	"Backstabber's Knife": {
		"type": "WEAPON",
		"icon": 1557,
		"level": 3,
		"goldCost": 1,
		"blurb": "",
		"coolDown": 0,
		"subType": "DAGGER",
		"material": "metal1",
		"stackSize": 1
	},
	"Blackfire Dagger": {
		"type": "WEAPON",
		"icon": 1558,
		"level": 4,
		"goldCost": 1,
		"blurb": "",
		"coolDown": 0,
		"subType": "DAGGER",
		"material": "metal1",
		"stackSize": 1
	},
	"Divine Toothpick": {
		"type": "WEAPON",
		"icon": 1559,
		"level": 5,
		"goldCost": 1,
		"blurb": "",
		"coolDown": 0,
		"subType": "DAGGER",
		"material": "metal1",
		"stackSize": 1
	},
	"Gut Ripper": {
		"type": "WEAPON",
		"icon": 1560,
		"level": 6,
		"goldCost": 1,
		"blurb": "",
		"coolDown": 0,
		"subType": "DAGGER",
		"material": "metal1",
		"stackSize": 1
	},
	"Enchanted Dagger": {
		"type": "WEAPON",
		"icon": 1561,
		"level": 7,
		"goldCost": 1,
		"blurb": "",
		"coolDown": 0,
		"subType": "DAGGER",
		"material": "metal1",
		"stackSize": 1
	},
	"Devil's Mercy": {
		"type": "WEAPON",
		"icon": 1562,
		"level": 8,
		"goldCost": 1,
		"blurb": "",
		"coolDown": 0,
		"subType": "DAGGER",
		"material": "metal1",
		"stackSize": 1
	},
	"Skull Carver": {
		"type": "WEAPON",
		"icon": 1563,
		"level": 9,
		"goldCost": 1,
		"blurb": "",
		"coolDown": 0,
		"subType": "DAGGER",
		"material": "metal1",
		"stackSize": 1
	},
	"Skin Shredder": {
		"type": "WEAPON",
		"icon": 1564,
		"level": 10,
		"goldCost": 1,
		"blurb": "",
		"coolDown": 0,
		"subType": "DAGGER",
		"material": "metal1",
		"stackSize": 1
	},
	"Farmer's Pike": {
		"type": "WEAPON",
		"icon": 1643,
		"level": 1,
		"goldCost": 1,
		"blurb": "",
		"coolDown": 0,
		"subType": "SPEAR",
		"material": "metal1",
		"stackSize": 1
	},
	"Jagged Pike": {
		"type": "WEAPON",
		"icon": 1647,
		"level": 2,
		"goldCost": 1,
		"blurb": "",
		"coolDown": 0,
		"subType": "SPEAR",
		"material": "metal1",
		"stackSize": 1
	},
	"Piercing Spear": {
		"type": "WEAPON",
		"icon": 1649,
		"level": 3,
		"goldCost": 1,
		"blurb": "",
		"coolDown": 0,
		"subType": "SPEAR",
		"material": "metal1",
		"stackSize": 1
	},
	"Shadowstrike": {
		"type": "WEAPON",
		"icon": 1650,
		"level": 4,
		"goldCost": 1,
		"blurb": "",
		"coolDown": 0,
		"subType": "SPEAR",
		"material": "metal1",
		"stackSize": 1
	},
	"Peacemaker": {
		"type": "WEAPON",
		"icon": 1651,
		"level": 5,
		"goldCost": 1,
		"blurb": "",
		"coolDown": 0,
		"subType": "SPEAR",
		"material": "metal1",
		"stackSize": 1
	},
	"Bloodpike": {
		"type": "WEAPON",
		"icon": 1652,
		"level": 6,
		"goldCost": 1,
		"blurb": "",
		"coolDown": 0,
		"subType": "SPEAR",
		"material": "metal1",
		"stackSize": 1
	},
	"Hope Killer": {
		"type": "WEAPON",
		"icon": 1653,
		"level": 7,
		"goldCost": 1,
		"blurb": "",
		"coolDown": 0,
		"subType": "SPEAR",
		"material": "metal1",
		"stackSize": 1
	},
	"Dreaded Stick": {
		"type": "WEAPON",
		"icon": 1654,
		"level": 8,
		"goldCost": 1,
		"blurb": "",
		"coolDown": 0,
		"subType": "SPEAR",
		"material": "metal1",
		"stackSize": 1
	},
	"Warlord's Glaive": {
		"type": "WEAPON",
		"icon": 1655,
		"level": 9,
		"goldCost": 1,
		"blurb": "",
		"coolDown": 0,
		"subType": "SPEAR",
		"material": "metal1",
		"stackSize": 1
	},
	"Bloodfall": {
		"type": "WEAPON",
		"icon": 1656,
		"level": 10,
		"goldCost": 1,
		"blurb": "",
		"coolDown": 0,
		"subType": "SPEAR",
		"material": "metal1",
		"stackSize": 1
	},
	"Primal Axe": {
		"type": "WEAPON",
		"icon": 1461,
		"level": 1,
		"goldCost": 1,
		"blurb": "",
		"coolDown": 0,
		"subType": "AXE",
		"material": "metal1",
		"stackSize": 1
	},
	"Chef's Cleaver": {
		"type": "WEAPON",
		"icon": 1465,
		"level": 2,
		"goldCost": 1,
		"blurb": "",
		"coolDown": 0,
		"subType": "AXE",
		"material": "metal1",
		"stackSize": 1
	},
	"Battle Axe": {
		"type": "WEAPON",
		"icon": 1467,
		"level": 3,
		"goldCost": 1,
		"blurb": "",
		"coolDown": 0,
		"subType": "AXE",
		"material": "metal1",
		"stackSize": 1
	},
	"Soul Hacker": {
		"type": "WEAPON",
		"icon": 1468,
		"level": 4,
		"goldCost": 1,
		"blurb": "",
		"coolDown": 0,
		"subType": "AXE",
		"material": "metal1",
		"stackSize": 1
	},
	"Head Chopper": {
		"type": "WEAPON",
		"icon": 1469,
		"level": 5,
		"goldCost": 1,
		"blurb": "",
		"coolDown": 0,
		"subType": "AXE",
		"material": "metal1",
		"stackSize": 1
	},
	"Decapitator": {
		"type": "WEAPON",
		"icon": 1470,
		"level": 6,
		"goldCost": 1,
		"blurb": "",
		"coolDown": 0,
		"subType": "AXE",
		"material": "metal1",
		"stackSize": 1
	},
	"Bone Chiller": {
		"type": "WEAPON",
		"icon": 1471,
		"level": 7,
		"goldCost": 1,
		"blurb": "",
		"coolDown": 0,
		"subType": "AXE",
		"material": "metal1",
		"stackSize": 1
	},
	"Howling Reaper": {
		"type": "WEAPON",
		"icon": 1472,
		"level": 8,
		"goldCost": 1,
		"blurb": "",
		"coolDown": 0,
		"subType": "AXE",
		"material": "metal1",
		"stackSize": 1
	},
	"Butcher's Friend": {
		"type": "WEAPON",
		"icon": 1473,
		"level": 9,
		"goldCost": 1,
		"blurb": "",
		"coolDown": 0,
		"subType": "AXE",
		"material": "metal1",
		"stackSize": 1
	},
	"Executioner's Final Word": {
		"type": "WEAPON",
		"icon": 1476,
		"level": 10,
		"goldCost": 1,
		"blurb": "",
		"coolDown": 0,
		"subType": "AXE",
		"material": "metal1",
		"stackSize": 1
	},
	"Pincers": {
		"type": "WEAPON",
		"icon": 1521,
		"level": 1,
		"goldCost": 1,
		"blurb": "",
		"coolDown": 0,
		"subType": "CLAW",
		"material": "metal1",
		"stackSize": 1
	},
	"Wolf's Paw": {
		"type": "WEAPON",
		"icon": 1525,
		"level": 2,
		"goldCost": 1,
		"blurb": "",
		"coolDown": 0,
		"subType": "CLAW",
		"material": "metal1",
		"stackSize": 1
	},
	"Spiked Knuckles": {
		"type": "WEAPON",
		"icon": 1527,
		"level": 3,
		"goldCost": 1,
		"blurb": "",
		"coolDown": 0,
		"subType": "CLAW",
		"material": "metal1",
		"stackSize": 1
	},
	"Death's Grip": {
		"type": "WEAPON",
		"icon": 1528,
		"level": 5,
		"goldCost": 1,
		"blurb": "",
		"coolDown": 0,
		"subType": "CLAW",
		"material": "metal1",
		"stackSize": 1
	},
	"Holy Fist": {
		"type": "WEAPON",
		"icon": 1529,
		"level": 6,
		"goldCost": 1,
		"blurb": "",
		"coolDown": 0,
		"subType": "CLAW",
		"material": "metal1",
		"stackSize": 1
	},
	"Tenderizer": {
		"type": "WEAPON",
		"icon": 1530,
		"level": 7,
		"goldCost": 1,
		"blurb": "",
		"coolDown": 0,
		"subType": "CLAW",
		"material": "metal1",
		"stackSize": 1
	},
	"Cold Hands": {
		"type": "WEAPON",
		"icon": 1531,
		"level": 8,
		"goldCost": 1,
		"blurb": "",
		"coolDown": 0,
		"subType": "CLAW",
		"material": "metal1",
		"stackSize": 1
	},
	"Bone Shredder": {
		"type": "WEAPON",
		"icon": 1532,
		"level": 9,
		"goldCost": 1,
		"blurb": "",
		"coolDown": 0,
		"subType": "CLAW",
		"material": "metal1",
		"stackSize": 1
	},
	"Claws of Agony": {
		"type": "WEAPON",
		"icon": 1533,
		"level": 10,
		"goldCost": 1,
		"blurb": "",
		"coolDown": 0,
		"subType": "CLAW",
		"material": "metal1",
		"stackSize": 1
	},
	"Large Club": {
		"type": "WEAPON",
		"icon": 1607,
		"level": 1,
		"goldCost": 1,
		"blurb": "",
		"coolDown": 0,
		"subType": "MACE",
		"material": "metal1",
		"stackSize": 1
	},
	"Warmaul": {
		"type": "WEAPON",
		"icon": 1611,
		"level": 2,
		"goldCost": 1,
		"blurb": "",
		"coolDown": 0,
		"subType": "MACE",
		"material": "metal1",
		"stackSize": 1
	},
	"Warhammer": {
		"type": "WEAPON",
		"icon": 1613,
		"level": 3,
		"goldCost": 1,
		"blurb": "",
		"coolDown": 0,
		"subType": "MACE",
		"material": "metal1",
		"stackSize": 1
	},
	"Grave Maker": {
		"type": "WEAPON",
		"icon": 1614,
		"level": 4,
		"goldCost": 1,
		"blurb": "",
		"coolDown": 0,
		"subType": "MACE",
		"material": "metal1",
		"stackSize": 1
	},
	"Oath Keeper": {
		"type": "WEAPON",
		"icon": 1615,
		"level": 5,
		"goldCost": 1,
		"blurb": "",
		"coolDown": 0,
		"subType": "MACE",
		"material": "metal1",
		"stackSize": 1
	},
	"Pain Bringer": {
		"type": "WEAPON",
		"icon": 1616,
		"level": 6,
		"goldCost": 1,
		"blurb": "",
		"coolDown": 0,
		"subType": "MACE",
		"material": "metal1",
		"stackSize": 1
	},
	"Celestial Rod": {
		"type": "WEAPON",
		"icon": 1617,
		"level": 7,
		"goldCost": 1,
		"blurb": "",
		"coolDown": 0,
		"subType": "MACE",
		"material": "metal1",
		"stackSize": 1
	},
	"Sorrow's End": {
		"type": "WEAPON",
		"icon": 1618,
		"level": 8,
		"goldCost": 1,
		"blurb": "",
		"coolDown": 0,
		"subType": "MACE",
		"material": "metal1",
		"stackSize": 1
	},
	"Breath Taker": {
		"type": "WEAPON",
		"icon": 1619,
		"level": 9,
		"goldCost": 1,
		"blurb": "",
		"coolDown": 0,
		"subType": "MACE",
		"material": "metal1",
		"stackSize": 1
	},
	"Annihilation": {
		"type": "WEAPON",
		"icon": 1621,
		"level": 10,
		"goldCost": 1,
		"blurb": "",
		"coolDown": 0,
		"subType": "MACE",
		"material": "metal1",
		"stackSize": 1
	},
	"Walking Cane": {
		"type": "WEAPON",
		"icon": 1663,
		"level": 1,
		"goldCost": 1,
		"blurb": "",
		"coolDown": 0,
		"subType": "STAFF",
		"material": "wood",
		"stackSize": 1
	},
	"Fighting Stick": {
		"type": "WEAPON",
		"icon": 1667,
		"level": 2,
		"goldCost": 1,
		"blurb": "",
		"coolDown": 0,
		"subType": "STAFF",
		"material": "wood",
		"stackSize": 1
	},
	"War Staff": {
		"type": "WEAPON",
		"icon": 1669,
		"level": 3,
		"goldCost": 1,
		"blurb": "",
		"coolDown": 0,
		"subType": "STAFF",
		"material": "wood",
		"stackSize": 1
	},
	"Scept of the Dead": {
		"type": "WEAPON",
		"icon": 1670,
		"level": 4,
		"goldCost": 1,
		"blurb": "",
		"coolDown": 0,
		"subType": "STAFF",
		"material": "wood",
		"stackSize": 1
	},
	"Light Bringer": {
		"type": "WEAPON",
		"icon": 1671,
		"level": 5,
		"goldCost": 1,
		"blurb": "",
		"coolDown": 0,
		"subType": "STAFF",
		"material": "wood",
		"stackSize": 1
	},
	"Tormented Scepter": {
		"type": "WEAPON",
		"icon": 1672,
		"level": 6,
		"goldCost": 1,
		"blurb": "",
		"coolDown": 0,
		"subType": "STAFF",
		"material": "wood",
		"stackSize": 1
	},
	"Spire of Hope": {
		"type": "WEAPON",
		"icon": 1673,
		"level": 7,
		"goldCost": 1,
		"blurb": "",
		"coolDown": 0,
		"subType": "STAFF",
		"material": "wood",
		"stackSize": 1
	},
	"Scept of the Ancients": {
		"type": "WEAPON",
		"icon": 1674,
		"level": 8,
		"goldCost": 1,
		"blurb": "",
		"coolDown": 0,
		"subType": "STAFF",
		"material": "wood",
		"stackSize": 1
	},
	"Staff of Damnation": {
		"type": "WEAPON",
		"icon": 1675,
		"level": 9,
		"goldCost": 1,
		"blurb": "",
		"coolDown": 0,
		"subType": "STAFF",
		"material": "wood",
		"stackSize": 1
	},
	"The Reckoning": {
		"type": "WEAPON",
		"icon": 1683,
		"level": 10,
		"goldCost": 1,
		"blurb": "",
		"coolDown": 0,
		"subType": "STAFF",
		"material": "wood",
		"stackSize": 1
	},
	"Needle Threader": {
		"type": "WEAPON",
		"icon": 1491,
		"level": 1,
		"goldCost": 1,
		"blurb": "",
		"coolDown": 0,
		"subType": "BOW",
		"material": "wood",
		"stackSize": 1
	},
	"Hunter's Bow": {
		"type": "WEAPON",
		"icon": 1495,
		"level": 2,
		"goldCost": 1,
		"blurb": "",
		"coolDown": 0,
		"subType": "BOW",
		"material": "wood",
		"stackSize": 1
	},
	"Repeating Longbow": {
		"type": "WEAPON",
		"icon": 1497,
		"level": 3,
		"goldCost": 1,
		"blurb": "",
		"coolDown": 0,
		"subType": "BOW",
		"material": "wood",
		"stackSize": 1
	},
	"Widowmaker": {
		"type": "WEAPON",
		"icon": 1498,
		"level": 4,
		"goldCost": 1,
		"blurb": "",
		"coolDown": 0,
		"subType": "BOW",
		"material": "wood",
		"stackSize": 1
	},
	"Angel's Harp": {
		"type": "WEAPON",
		"icon": 1499,
		"level": 5,
		"goldCost": 1,
		"blurb": "",
		"coolDown": 0,
		"subType": "BOW",
		"material": "wood",
		"stackSize": 1
	},
	"Bloodseeker": {
		"type": "WEAPON",
		"icon": 1500,
		"level": 6,
		"goldCost": 1,
		"blurb": "",
		"coolDown": 0,
		"subType": "BOW",
		"material": "wood",
		"stackSize": 1
	},
	"Chord of Justice": {
		"type": "WEAPON",
		"icon": 1501,
		"level": 7,
		"goldCost": 1,
		"blurb": "",
		"coolDown": 0,
		"subType": "BOW",
		"material": "wood",
		"stackSize": 1
	},
	"Last Kiss": {
		"type": "WEAPON",
		"icon": 1502,
		"level": 8,
		"goldCost": 1,
		"blurb": "",
		"coolDown": 0,
		"subType": "BOW",
		"material": "wood",
		"stackSize": 1
	},
	"High Strung": {
		"type": "WEAPON",
		"icon": 1506,
		"level": 9,
		"goldCost": 1,
		"blurb": "",
		"coolDown": 0,
		"subType": "BOW",
		"material": "wood",
		"stackSize": 1
	},
	"Throat Needler": {
		"type": "WEAPON",
		"icon": 1508,
		"level": 10,
		"goldCost": 1,
		"blurb": "",
		"coolDown": 0,
		"subType": "BOW",
		"material": "wood",
		"stackSize": 1
	},
	"Linen Robe": {
		"type": "ARMOR",
		"icon": 56,
		"level": 1,
		"goldCost": 1,
		"blurb": "",
		"coolDown": 0,
		"subType": "",
		"material": "cloth",
		"stackSize": 1
	},
	"Scout's Cloak": {
		"type": "ARMOR",
		"icon": 88,
		"level": 1,
		"goldCost": 1,
		"blurb": "",
		"coolDown": 0,
		"subType": "",
		"material": "cloth",
		"stackSize": 1
	},
	"Chainvest": {
		"type": "ARMOR",
		"icon": 91,
		"level": 2,
		"goldCost": 1,
		"blurb": "",
		"coolDown": 0,
		"subType": "",
		"material": "metal0",
		"stackSize": 1
	},
	"Leather Vest": {
		"type": "ARMOR",
		"icon": 59,
		"level": 2,
		"goldCost": 1,
		"blurb": "",
		"coolDown": 0,
		"subType": "",
		"material": "cloth",
		"stackSize": 1
	},
	"Leather Breastplate": {
		"type": "ARMOR",
		"icon": 60,
		"level": 3,
		"goldCost": 1,
		"blurb": "",
		"coolDown": 0,
		"subType": "",
		"material": "cloth",
		"stackSize": 1
	},
	"Studded Leather Tunic": {
		"type": "ARMOR",
		"icon": 72,
		"level": 3,
		"goldCost": 1,
		"blurb": "",
		"coolDown": 0,
		"subType": "",
		"material": "cloth",
		"stackSize": 1
	},
	"Tarnished Plate Vest": {
		"type": "ARMOR",
		"icon": 61,
		"level": 4,
		"goldCost": 1,
		"blurb": "",
		"coolDown": 0,
		"subType": "",
		"material": "metal0",
		"stackSize": 1
	},
	"Embroidered Leather Armor": {
		"type": "ARMOR",
		"icon": 161,
		"level": 4,
		"goldCost": 1,
		"blurb": "",
		"coolDown": 0,
		"subType": "",
		"material": "cloth",
		"stackSize": 1
	},
	"Platemail Armor": {
		"type": "ARMOR",
		"icon": 73,
		"level": 5,
		"goldCost": 1,
		"blurb": "",
		"coolDown": 0,
		"subType": "",
		"material": "metal0",
		"stackSize": 1
	},
	"Metal Tunic": {
		"type": "ARMOR",
		"icon": 68,
		"level": 5,
		"goldCost": 1,
		"blurb": "",
		"coolDown": 0,
		"subType": "",
		"material": "metal0",
		"stackSize": 1
	},
	"Vanguard Breastplate": {
		"type": "ARMOR",
		"icon": 62,
		"level": 6,
		"goldCost": 1,
		"blurb": "",
		"coolDown": 0,
		"subType": "",
		"material": "metal0",
		"stackSize": 1
	},
	"Steelforged Chestguard": {
		"type": "ARMOR",
		"icon": 124,
		"level": 6,
		"goldCost": 1,
		"blurb": "",
		"coolDown": 0,
		"subType": "",
		"material": "metal0",
		"stackSize": 1
	},
	"Warlord's Cuirass": {
		"type": "ARMOR",
		"icon": 64,
		"level": 7,
		"goldCost": 1,
		"blurb": "",
		"coolDown": 0,
		"subType": "",
		"material": "metal0",
		"stackSize": 1
	},
	"Embroidered Armor": {
		"type": "ARMOR",
		"icon": 148,
		"level": 7,
		"goldCost": 1,
		"blurb": "",
		"coolDown": 0,
		"subType": "",
		"material": "metal0",
		"stackSize": 1
	},
	"Ceremonial Breastplate": {
		"type": "ARMOR",
		"icon": 63,
		"level": 8,
		"goldCost": 1,
		"blurb": "",
		"coolDown": 0,
		"subType": "",
		"material": "metal0",
		"stackSize": 1
	},
	"Heavy Plated Armor": {
		"type": "ARMOR",
		"icon": 76,
		"level": 8,
		"goldCost": 1,
		"blurb": "",
		"coolDown": 0,
		"subType": "",
		"material": "metal0",
		"stackSize": 1
	},
	"Ancient Oriental Breastplate": {
		"type": "ARMOR",
		"icon": 75,
		"level": 9,
		"goldCost": 1,
		"blurb": "",
		"coolDown": 0,
		"subType": "",
		"material": "metal0",
		"stackSize": 1
	},
	"Polished Chestplate": {
		"type": "ARMOR",
		"icon": 151,
		"level": 9,
		"goldCost": 1,
		"blurb": "",
		"coolDown": 0,
		"subType": "",
		"material": "metal0",
		"stackSize": 1
	},
	"Immortal's Armor": {
		"type": "ARMOR",
		"icon": 78,
		"level": 10,
		"goldCost": 1,
		"blurb": "",
		"coolDown": 0,
		"subType": "",
		"material": "metal0",
		"stackSize": 1
	},
	"Juggernaut Breastplate": {
		"type": "ARMOR",
		"icon": 67,
		"level": 10,
		"goldCost": 1,
		"blurb": "",
		"coolDown": 0,
		"subType": "",
		"material": "metal0",
		"stackSize": 1
	},
	"Macho Banana": {
		"type": "FOOD",
		"icon": 262,
		"level": 1,
		"goldCost": 1,
		"blurb": "",
		"coolDown": 0,
		"subType": "",
		"material": "misc",
		"stackSize": 10
	},
	"Roasted Carrot": {
		"type": "FOOD",
		"icon": 305,
		"level": 1,
		"goldCost": 1,
		"blurb": "",
		"coolDown": 0,
		"subType": "",
		"material": "misc",
		"stackSize": 10
	},
	"Angel Peach": {
		"type": "FOOD",
		"icon": 260,
		"level": 2,
		"goldCost": 1,
		"blurb": "",
		"coolDown": 0,
		"subType": "",
		"material": "misc",
		"stackSize": 10
	},
	"Juicy Apple": {
		"type": "FOOD",
		"icon": 257,
		"level": 2,
		"goldCost": 1,
		"blurb": "",
		"coolDown": 0,
		"subType": "",
		"material": "misc",
		"stackSize": 10
	},
	"Moonberry": {
		"type": "FOOD",
		"icon": 263,
		"level": 3,
		"goldCost": 1,
		"blurb": "",
		"coolDown": 0,
		"subType": "",
		"material": "misc",
		"stackSize": 10
	},
	"Grizzly Grapes": {
		"type": "FOOD",
		"icon": 308,
		"level": 3,
		"goldCost": 1,
		"blurb": "",
		"coolDown": 0,
		"subType": "",
		"material": "misc",
		"stackSize": 10
	},
	"Ripe Watermelon": {
		"type": "FOOD",
		"icon": 264,
		"level": 4,
		"goldCost": 1,
		"blurb": "",
		"coolDown": 0,
		"subType": "",
		"material": "misc",
		"stackSize": 10
	},
	"Sweet Pineapple": {
		"type": "FOOD",
		"icon": 261,
		"level": 4,
		"goldCost": 1,
		"blurb": "",
		"coolDown": 0,
		"subType": "",
		"material": "misc",
		"stackSize": 10
	},
	"Corn on the Cob": {
		"type": "FOOD",
		"icon": 313,
		"level": 5,
		"goldCost": 1,
		"blurb": "",
		"coolDown": 0,
		"subType": "",
		"material": "misc",
		"stackSize": 10
	},
	"Nutty Acorn": {
		"type": "FOOD",
		"icon": 321,
		"level": 5,
		"goldCost": 1,
		"blurb": "",
		"coolDown": 0,
		"subType": "",
		"material": "misc",
		"stackSize": 10
	},
	"Sun Dried Mushroom": {
		"type": "FOOD",
		"icon": 310,
		"level": 6,
		"goldCost": 1,
		"blurb": "",
		"coolDown": 0,
		"subType": "",
		"material": "misc",
		"stackSize": 10
	},
	"Herb Baked Egg": {
		"type": "FOOD",
		"icon": 291,
		"level": 6,
		"goldCost": 1,
		"blurb": "",
		"coolDown": 0,
		"subType": "",
		"material": "misc",
		"stackSize": 10
	},
	"Hard Cheese": {
		"type": "FOOD",
		"icon": 289,
		"level": 7,
		"goldCost": 1,
		"blurb": "",
		"coolDown": 0,
		"subType": "",
		"material": "misc",
		"stackSize": 10
	},
	"Spice Bread": {
		"type": "FOOD",
		"icon": 297,
		"level": 7,
		"goldCost": 1,
		"blurb": "",
		"coolDown": 0,
		"subType": "",
		"material": "misc",
		"stackSize": 10
	},
	"Oatmeal Muffin": {
		"type": "FOOD",
		"icon": 327,
		"level": 8,
		"goldCost": 1,
		"blurb": "",
		"coolDown": 0,
		"subType": "",
		"material": "misc",
		"stackSize": 10
	},
	"Chocolate Chip Cookie": {
		"type": "FOOD",
		"icon": 273,
		"level": 8,
		"goldCost": 1,
		"blurb": "",
		"coolDown": 0,
		"subType": "",
		"material": "misc",
		"stackSize": 10
	},
	"Queenfish": {
		"type": "FOOD",
		"icon": 292,
		"level": 9,
		"goldCost": 1,
		"blurb": "",
		"coolDown": 0,
		"subType": "",
		"material": "misc",
		"stackSize": 10
	},
	"Massive Chicken Leg": {
		"type": "FOOD",
		"icon": 293,
		"level": 9,
		"goldCost": 1,
		"blurb": "",
		"coolDown": 0,
		"subType": "",
		"material": "misc",
		"stackSize": 10
	},
	"Marinated Steak": {
		"type": "FOOD",
		"icon": 304,
		"level": 10,
		"goldCost": 1,
		"blurb": "",
		"coolDown": 0,
		"subType": "",
		"material": "misc",
		"stackSize": 10
	},
	"Bowl of Honey": {
		"type": "FOOD",
		"icon": 280,
		"level": 10,
		"goldCost": 1,
		"blurb": "",
		"coolDown": 0,
		"subType": "",
		"material": "misc",
		"stackSize": 10
	},
	"Spider Fang": {
		"type": "MISC",
		"icon": 217,
		"level": 1,
		"goldCost": 1,
		"blurb": "",
		"coolDown": 0,
		"subType": "",
		"material": "misc",
		"stackSize": 10
	},
	"Light Feather": {
		"type": "MISC",
		"icon": 213,
		"level": 1,
		"goldCost": 1,
		"blurb": "",
		"coolDown": 0,
		"subType": "",
		"material": "misc",
		"stackSize": 10
	},
	"Brown Button": {
		"type": "MISC",
		"icon": 230,
		"level": 2,
		"goldCost": 1,
		"blurb": "",
		"coolDown": 0,
		"subType": "",
		"material": "misc",
		"stackSize": 10
	},
	"Petrified Bone": {
		"type": "MISC",
		"icon": 201,
		"level": 2,
		"goldCost": 1,
		"blurb": "",
		"coolDown": 0,
		"subType": "",
		"material": "misc",
		"stackSize": 10
	},
	"Seashell": {
		"type": "MISC",
		"icon": 214,
		"level": 3,
		"goldCost": 1,
		"blurb": "",
		"coolDown": 0,
		"subType": "",
		"material": "misc",
		"stackSize": 10
	},
	"Bat Ear": {
		"type": "MISC",
		"icon": 204,
		"level": 3,
		"goldCost": 1,
		"blurb": "",
		"coolDown": 0,
		"subType": "",
		"material": "misc",
		"stackSize": 10
	},
	"Crab Pincer": {
		"type": "MISC",
		"icon": 205,
		"level": 4,
		"goldCost": 1,
		"blurb": "",
		"coolDown": 0,
		"subType": "",
		"material": "misc",
		"stackSize": 10
	},
	"Cat Eye": {
		"type": "MISC",
		"icon": 218,
		"level": 4,
		"goldCost": 1,
		"blurb": "",
		"coolDown": 0,
		"subType": "",
		"material": "misc",
		"stackSize": 10
	},
	"Blue Feather": {
		"type": "MISC",
		"icon": 197,
		"level": 5,
		"goldCost": 1,
		"blurb": "",
		"coolDown": 0,
		"subType": "",
		"material": "misc",
		"stackSize": 10
	},
	"Candle": {
		"type": "MISC",
		"icon": 240,
		"level": 5,
		"goldCost": 1,
		"blurb": "",
		"coolDown": 0,
		"subType": "",
		"material": "misc",
		"stackSize": 10
	},
	"Rugged Leather": {
		"type": "MISC",
		"icon": 195,
		"level": 6,
		"goldCost": 1,
		"blurb": "",
		"coolDown": 0,
		"subType": "",
		"material": "misc",
		"stackSize": 10
	},
	"Course Leather": {
		"type": "MISC",
		"icon": 210,
		"level": 6,
		"goldCost": 1,
		"blurb": "",
		"coolDown": 0,
		"subType": "",
		"material": "misc",
		"stackSize": 10
	},
	"Wolf Tail": {
		"type": "MISC",
		"icon": 222,
		"level": 7,
		"goldCost": 1,
		"blurb": "",
		"coolDown": 0,
		"subType": "",
		"material": "misc",
		"stackSize": 10
	},
	"Shattered Mirror": {
		"type": "MISC",
		"icon": 243,
		"level": 7,
		"goldCost": 1,
		"blurb": "",
		"coolDown": 0,
		"subType": "",
		"material": "misc",
		"stackSize": 10
	},
	"Cat Claw": {
		"type": "MISC",
		"icon": 196,
		"level": 8,
		"goldCost": 1,
		"blurb": "",
		"coolDown": 0,
		"subType": "",
		"material": "misc",
		"stackSize": 10
	},
	"Metal Plate": {
		"type": "MISC",
		"icon": 225,
		"level": 8,
		"goldCost": 1,
		"blurb": "",
		"coolDown": 0,
		"subType": "",
		"material": "misc",
		"stackSize": 10
	},
	"Canine": {
		"type": "MISC",
		"icon": 193,
		"level": 9,
		"goldCost": 1,
		"blurb": "",
		"coolDown": 0,
		"subType": "",
		"material": "misc",
		"stackSize": 10
	},
	"Ruined Pelt": {
		"type": "MISC",
		"icon": 194,
		"level": 9,
		"goldCost": 1,
		"blurb": "",
		"coolDown": 0,
		"subType": "",
		"material": "misc",
		"stackSize": 10
	},
	"Red Yarn": {
		"type": "MISC",
		"icon": 229,
		"level": 10,
		"goldCost": 1,
		"blurb": "",
		"coolDown": 0,
		"subType": "",
		"material": "misc",
		"stackSize": 10
	},
	"Broken Glass": {
		"type": "MISC",
		"icon": 813,
		"level": 10,
		"goldCost": 1,
		"blurb": "",
		"coolDown": 0,
		"subType": "",
		"material": "misc",
		"stackSize": 10
	},
	"Minor Healing Potion": {
		"type": "POTION",
		"icon": 800,
		"level": 1,
		"goldCost": 1,
		"blurb": "",
		"coolDown": 0,
		"subType": "HEALING",
		"material": "glass",
		"stackSize": 5
	},
	"Minor Mana Potion": {
		"type": "POTION",
		"icon": 805,
		"level": 1,
		"goldCost": 1,
		"blurb": "",
		"coolDown": 0,
		"subType": "MANA",
		"material": "glass",
		"stackSize": 5
	},
	"Elixir of Minor Stamina": {
		"type": "POTION",
		"icon": 801,
		"level": 1,
		"goldCost": 1,
		"blurb": "",
		"coolDown": 0,
		"subType": "STAMINA",
		"material": "glass",
		"stackSize": 5
	},
	"Elixir of Minor Intellect": {
		"type": "POTION",
		"icon": 806,
		"level": 1,
		"goldCost": 1,
		"blurb": "",
		"coolDown": 0,
		"subType": "INTELLECT",
		"material": "glass",
		"stackSize": 5
	},
	"Elixir of Minor Agility": {
		"type": "POTION",
		"icon": 803,
		"level": 1,
		"goldCost": 1,
		"blurb": "",
		"coolDown": 0,
		"subType": "AGILITY",
		"material": "glass",
		"stackSize": 5
	},
	"Elixir of Minor Strength": {
		"type": "POTION",
		"icon": 802,
		"level": 1,
		"goldCost": 1,
		"blurb": "",
		"coolDown": 0,
		"subType": "STRENGTH",
		"material": "glass",
		"stackSize": 5
	},
	"Elixir of Minor Defense": {
		"type": "POTION",
		"icon": 809,
		"level": 1,
		"goldCost": 1,
		"blurb": "",
		"coolDown": 0,
		"subType": "DEFENSE",
		"material": "glass",
		"stackSize": 5
	},
	"Lesser Healing Potion": {
		"type": "POTION",
		"icon": 786,
		"level": 2,
		"goldCost": 1,
		"blurb": "",
		"coolDown": 0,
		"subType": "HEALING",
		"material": "glass",
		"stackSize": 5
	},
	"Lesser Mana Potion": {
		"type": "POTION",
		"icon": 791,
		"level": 2,
		"goldCost": 1,
		"blurb": "",
		"coolDown": 0,
		"subType": "MANA",
		"material": "glass",
		"stackSize": 5
	},
	"Elixir of Lesser Stamina": {
		"type": "POTION",
		"icon": 787,
		"level": 2,
		"goldCost": 1,
		"blurb": "",
		"coolDown": 0,
		"subType": "STAMINA",
		"material": "glass",
		"stackSize": 5
	},
	"Elixir of Lesser Intellect": {
		"type": "POTION",
		"icon": 792,
		"level": 2,
		"goldCost": 1,
		"blurb": "",
		"coolDown": 0,
		"subType": "INTELLECT",
		"material": "glass",
		"stackSize": 5
	},
	"Elixir of Lesser Agility": {
		"type": "POTION",
		"icon": 789,
		"level": 2,
		"goldCost": 1,
		"blurb": "",
		"coolDown": 0,
		"subType": "AGILITY",
		"material": "glass",
		"stackSize": 5
	},
	"Elixir of Lesser Strength": {
		"type": "POTION",
		"icon": 788,
		"level": 2,
		"goldCost": 1,
		"blurb": "",
		"coolDown": 0,
		"subType": "STRENGTH",
		"material": "glass",
		"stackSize": 5
	},
	"Elixir of Lesser Defense": {
		"type": "POTION",
		"icon": 795,
		"level": 2,
		"goldCost": 1,
		"blurb": "",
		"coolDown": 0,
		"subType": "DEFENSE",
		"material": "glass",
		"stackSize": 5
	},
	"Healing Potion": {
		"type": "POTION",
		"icon": 604,
		"level": 3,
		"goldCost": 1,
		"blurb": "",
		"coolDown": 0,
		"subType": "HEALING",
		"material": "glass",
		"stackSize": 5
	},
	"Mana Potion": {
		"type": "POTION",
		"icon": 609,
		"level": 3,
		"goldCost": 1,
		"blurb": "",
		"coolDown": 0,
		"subType": "MANA",
		"material": "glass",
		"stackSize": 5
	},
	"Elixir of Stamina": {
		"type": "POTION",
		"icon": 605,
		"level": 3,
		"goldCost": 1,
		"blurb": "",
		"coolDown": 0,
		"subType": "STAMINA",
		"material": "glass",
		"stackSize": 5
	},
	"Elixir of Intellect": {
		"type": "POTION",
		"icon": 610,
		"level": 3,
		"goldCost": 1,
		"blurb": "",
		"coolDown": 0,
		"subType": "INTELLECT",
		"material": "glass",
		"stackSize": 5
	},
	"Elixir of Agility": {
		"type": "POTION",
		"icon": 607,
		"level": 3,
		"goldCost": 1,
		"blurb": "",
		"coolDown": 0,
		"subType": "AGILITY",
		"material": "glass",
		"stackSize": 5
	},
	"Elixir of Strength": {
		"type": "POTION",
		"icon": 606,
		"level": 3,
		"goldCost": 1,
		"blurb": "",
		"coolDown": 0,
		"subType": "STRENGTH",
		"material": "glass",
		"stackSize": 5
	},
	"Elixir of Defense": {
		"type": "POTION",
		"icon": 613,
		"level": 3,
		"goldCost": 1,
		"blurb": "",
		"coolDown": 0,
		"subType": "DEFENSE",
		"material": "glass",
		"stackSize": 5
	},
	"Greater Healing Potion": {
		"type": "POTION",
		"icon": 646,
		"level": 4,
		"goldCost": 1,
		"blurb": "",
		"coolDown": 0,
		"subType": "HEALING",
		"material": "glass",
		"stackSize": 5
	},
	"Greater Mana Potion": {
		"type": "POTION",
		"icon": 651,
		"level": 4,
		"goldCost": 1,
		"blurb": "",
		"coolDown": 0,
		"subType": "MANA",
		"material": "glass",
		"stackSize": 5
	},
	"Elixir of Greater Stamina": {
		"type": "POTION",
		"icon": 647,
		"level": 4,
		"goldCost": 1,
		"blurb": "",
		"coolDown": 0,
		"subType": "STAMINA",
		"material": "glass",
		"stackSize": 5
	},
	"Elixir of Greater Intellect": {
		"type": "POTION",
		"icon": 652,
		"level": 4,
		"goldCost": 1,
		"blurb": "",
		"coolDown": 0,
		"subType": "INTELLECT",
		"material": "glass",
		"stackSize": 5
	},
	"Elixir of Greater Agility": {
		"type": "POTION",
		"icon": 649,
		"level": 4,
		"goldCost": 1,
		"blurb": "",
		"coolDown": 0,
		"subType": "AGILITY",
		"material": "glass",
		"stackSize": 5
	},
	"Elixir of Greater Strength": {
		"type": "POTION",
		"icon": 648,
		"level": 4,
		"goldCost": 1,
		"blurb": "",
		"coolDown": 0,
		"subType": "STRENGTH",
		"material": "glass",
		"stackSize": 5
	},
	"Elixir of Greater Defense": {
		"type": "POTION",
		"icon": 655,
		"level": 4,
		"goldCost": 1,
		"blurb": "",
		"coolDown": 0,
		"subType": "DEFENSE",
		"material": "glass",
		"stackSize": 5
	},
	"Superior Healing Potion": {
		"type": "POTION",
		"icon": 618,
		"level": 5,
		"goldCost": 1,
		"blurb": "",
		"coolDown": 0,
		"subType": "HEALING",
		"material": "glass",
		"stackSize": 5
	},
	"Superior Mana Potion": {
		"type": "POTION",
		"icon": 623,
		"level": 5,
		"goldCost": 1,
		"blurb": "",
		"coolDown": 0,
		"subType": "MANA",
		"material": "glass",
		"stackSize": 5
	},
	"Elixir of Superior Stamina": {
		"type": "POTION",
		"icon": 619,
		"level": 5,
		"goldCost": 1,
		"blurb": "",
		"coolDown": 0,
		"subType": "STAMINA",
		"material": "glass",
		"stackSize": 5
	},
	"Elixir of Superior Intellect": {
		"type": "POTION",
		"icon": 624,
		"level": 5,
		"goldCost": 1,
		"blurb": "",
		"coolDown": 0,
		"subType": "INTELLECT",
		"material": "glass",
		"stackSize": 5
	},
	"Elixir of Superior Agility": {
		"type": "POTION",
		"icon": 621,
		"level": 5,
		"goldCost": 1,
		"blurb": "",
		"coolDown": 0,
		"subType": "AGILITY",
		"material": "glass",
		"stackSize": 5
	},
	"Elixir of Superior Strength": {
		"type": "POTION",
		"icon": 620,
		"level": 5,
		"goldCost": 1,
		"blurb": "",
		"coolDown": 0,
		"subType": "STRENGTH",
		"material": "glass",
		"stackSize": 5
	},
	"Elixir of Superior Defense": {
		"type": "POTION",
		"icon": 627,
		"level": 5,
		"goldCost": 1,
		"blurb": "",
		"coolDown": 0,
		"subType": "DEFENSE",
		"material": "glass",
		"stackSize": 5
	},
	"Major Healing Potion": {
		"type": "POTION",
		"icon": 744,
		"level": 6,
		"goldCost": 1,
		"blurb": "",
		"coolDown": 0,
		"subType": "HEALING",
		"material": "glass",
		"stackSize": 5
	},
	"Major Mana Potion": {
		"type": "POTION",
		"icon": 749,
		"level": 6,
		"goldCost": 1,
		"blurb": "",
		"coolDown": 0,
		"subType": "MANA",
		"material": "glass",
		"stackSize": 5
	},
	"Elixir of Major Stamina": {
		"type": "POTION",
		"icon": 745,
		"level": 6,
		"goldCost": 1,
		"blurb": "",
		"coolDown": 0,
		"subType": "STAMINA",
		"material": "glass",
		"stackSize": 5
	},
	"Elixir of Major Intellect": {
		"type": "POTION",
		"icon": 750,
		"level": 6,
		"goldCost": 1,
		"blurb": "",
		"coolDown": 0,
		"subType": "INTELLECT",
		"material": "glass",
		"stackSize": 5
	},
	"Elixir of Major Agility": {
		"type": "POTION",
		"icon": 747,
		"level": 6,
		"goldCost": 1,
		"blurb": "",
		"coolDown": 0,
		"subType": "AGILITY",
		"material": "glass",
		"stackSize": 5
	},
	"Elixir of Major Strength": {
		"type": "POTION",
		"icon": 746,
		"level": 6,
		"goldCost": 1,
		"blurb": "",
		"coolDown": 0,
		"subType": "STRENGTH",
		"material": "glass",
		"stackSize": 5
	},
	"Elixir of Major Defense": {
		"type": "POTION",
		"icon": 753,
		"level": 6,
		"goldCost": 1,
		"blurb": "",
		"coolDown": 0,
		"subType": "DEFENSE",
		"material": "glass",
		"stackSize": 5
	},
	"Master Healing Potion": {
		"type": "POTION",
		"icon": 772,
		"level": 7,
		"goldCost": 1,
		"blurb": "",
		"coolDown": 0,
		"subType": "HEALING",
		"material": "glass",
		"stackSize": 5
	},
	"Master Mana Potion": {
		"type": "POTION",
		"icon": 777,
		"level": 7,
		"goldCost": 1,
		"blurb": "",
		"coolDown": 0,
		"subType": "MANA",
		"material": "glass",
		"stackSize": 5
	},
	"Elixir of Master Stamina": {
		"type": "POTION",
		"icon": 773,
		"level": 7,
		"goldCost": 1,
		"blurb": "",
		"coolDown": 0,
		"subType": "STAMINA",
		"material": "glass",
		"stackSize": 5
	},
	"Elixir of Master Intellect": {
		"type": "POTION",
		"icon": 778,
		"level": 7,
		"goldCost": 1,
		"blurb": "",
		"coolDown": 0,
		"subType": "INTELLECT",
		"material": "glass",
		"stackSize": 5
	},
	"Elixir of Master Agility": {
		"type": "POTION",
		"icon": 775,
		"level": 7,
		"goldCost": 1,
		"blurb": "",
		"coolDown": 0,
		"subType": "AGILITY",
		"material": "glass",
		"stackSize": 5
	},
	"Elixir of Master Strength": {
		"type": "POTION",
		"icon": 774,
		"level": 7,
		"goldCost": 1,
		"blurb": "",
		"coolDown": 0,
		"subType": "STRENGTH",
		"material": "glass",
		"stackSize": 5
	},
	"Elixir of Master Defense": {
		"type": "POTION",
		"icon": 781,
		"level": 7,
		"goldCost": 1,
		"blurb": "",
		"coolDown": 0,
		"subType": "DEFENSE",
		"material": "glass",
		"stackSize": 5
	},
	"Legendary Healing Potion": {
		"type": "POTION",
		"icon": 590,
		"level": 8,
		"goldCost": 1,
		"blurb": "",
		"coolDown": 0,
		"subType": "HEALING",
		"material": "glass",
		"stackSize": 5
	},
	"Legendary Mana Potion": {
		"type": "POTION",
		"icon": 595,
		"level": 8,
		"goldCost": 1,
		"blurb": "",
		"coolDown": 0,
		"subType": "MANA",
		"material": "glass",
		"stackSize": 5
	},
	"Elixir of Legendary Stamina": {
		"type": "POTION",
		"icon": 591,
		"level": 8,
		"goldCost": 1,
		"blurb": "",
		"coolDown": 0,
		"subType": "STAMINA",
		"material": "glass",
		"stackSize": 5
	},
	"Elixir of Legendary Intellect": {
		"type": "POTION",
		"icon": 596,
		"level": 8,
		"goldCost": 1,
		"blurb": "",
		"coolDown": 0,
		"subType": "INTELLECT",
		"material": "glass",
		"stackSize": 5
	},
	"Elixir of Legendary Agility": {
		"type": "POTION",
		"icon": 593,
		"level": 8,
		"goldCost": 1,
		"blurb": "",
		"coolDown": 0,
		"subType": "AGILITY",
		"material": "glass",
		"stackSize": 5
	},
	"Elixir of Legendary Strength": {
		"type": "POTION",
		"icon": 592,
		"level": 8,
		"goldCost": 1,
		"blurb": "",
		"coolDown": 0,
		"subType": "STRENGTH",
		"material": "glass",
		"stackSize": 5
	},
	"Elixir of Legendary Defense": {
		"type": "POTION",
		"icon": 599,
		"level": 8,
		"goldCost": 1,
		"blurb": "",
		"coolDown": 0,
		"subType": "DEFENSE",
		"material": "glass",
		"stackSize": 5
	},
	"Mythical Healing Potion": {
		"type": "POTION",
		"icon": 688,
		"level": 9,
		"goldCost": 1,
		"blurb": "",
		"coolDown": 0,
		"subType": "HEALING",
		"material": "glass",
		"stackSize": 5
	},
	"Mythical Mana Potion": {
		"type": "POTION",
		"icon": 693,
		"level": 9,
		"goldCost": 1,
		"blurb": "",
		"coolDown": 0,
		"subType": "MANA",
		"material": "glass",
		"stackSize": 5
	},
	"Elixir of Mythical Stamina": {
		"type": "POTION",
		"icon": 689,
		"level": 9,
		"goldCost": 1,
		"blurb": "",
		"coolDown": 0,
		"subType": "STAMINA",
		"material": "glass",
		"stackSize": 5
	},
	"Elixir of Mythical Intellect": {
		"type": "POTION",
		"icon": 694,
		"level": 9,
		"goldCost": 1,
		"blurb": "",
		"coolDown": 0,
		"subType": "INTELLECT",
		"material": "glass",
		"stackSize": 5
	},
	"Elixir of Mythical Agility": {
		"type": "POTION",
		"icon": 691,
		"level": 9,
		"goldCost": 1,
		"blurb": "",
		"coolDown": 0,
		"subType": "AGILITY",
		"material": "glass",
		"stackSize": 5
	},
	"Elixir of Mythical Strength": {
		"type": "POTION",
		"icon": 690,
		"level": 9,
		"goldCost": 1,
		"blurb": "",
		"coolDown": 0,
		"subType": "STRENGTH",
		"material": "glass",
		"stackSize": 5
	},
	"Elixir of Mythical Defense": {
		"type": "POTION",
		"icon": 697,
		"level": 9,
		"goldCost": 1,
		"blurb": "",
		"coolDown": 0,
		"subType": "DEFENSE",
		"material": "glass",
		"stackSize": 5
	},
	"Ancient Healing Potion": {
		"type": "POTION",
		"icon": 758,
		"level": 10,
		"goldCost": 1,
		"blurb": "",
		"coolDown": 0,
		"subType": "HEALING",
		"material": "glass",
		"stackSize": 5
	},
	"Ancient Mana Potion": {
		"type": "POTION",
		"icon": 763,
		"level": 10,
		"goldCost": 1,
		"blurb": "",
		"coolDown": 0,
		"subType": "MANA",
		"material": "glass",
		"stackSize": 5
	},
	"Elixir of Ancient Stamina": {
		"type": "POTION",
		"icon": 759,
		"level": 10,
		"goldCost": 1,
		"blurb": "",
		"coolDown": 0,
		"subType": "STAMINA",
		"material": "glass",
		"stackSize": 5
	},
	"Elixir of Ancient Intellect": {
		"type": "POTION",
		"icon": 764,
		"level": 10,
		"goldCost": 1,
		"blurb": "",
		"coolDown": 0,
		"subType": "INTELLECT",
		"material": "glass",
		"stackSize": 5
	},
	"Elixir of Ancient Agility": {
		"type": "POTION",
		"icon": 761,
		"level": 10,
		"goldCost": 1,
		"blurb": "",
		"coolDown": 0,
		"subType": "AGILITY",
		"material": "glass",
		"stackSize": 5
	},
	"Elixir of Ancient Strength": {
		"type": "POTION",
		"icon": 760,
		"level": 10,
		"goldCost": 1,
		"blurb": "",
		"coolDown": 0,
		"subType": "STRENGTH",
		"material": "glass",
		"stackSize": 5
	},
	"Elixir of Ancient Defense": {
		"type": "POTION",
		"icon": 767,
		"level": 10,
		"goldCost": 1,
		"blurb": "",
		"coolDown": 0,
		"subType": "DEFENSE",
		"material": "glass",
		"stackSize": 5
	}
}